latex_snippet-0.3.0.dist-info/METADATA
latex_snippet-0.3.0.dist-info/WHEEL
latex_snippet/__pycache__/__init__.cpython-35.pyc
latex_snippet/__pycache__/__init__.cpython-37.pyc
latex_snippet/__init__.py~
latex_snippet/__init__.py
latex_snippet/latex_snippet/__init__.py
latex_snippet/latex_snippet/ffi.py
latex_snippet/latex_snippet/native.so
latex_snippet-0.3.0.dist-info/RECORD
